auto_gpg/__init__.py
auto_gpg/cli.py
auto_gpg-0.1.0.dist-info/LICENSE
auto_gpg-0.1.0.dist-info/METADATA
auto_gpg-0.1.0.dist-info/WHEEL
auto_gpg-0.1.0.dist-info/entry_points.txt
auto_gpg-0.1.0.dist-info/top_level.txt
auto_gpg-0.1.0.dist-info/RECORD
