Metadata-Version: 2.1
Name: auto-gpg
Version: 0.1.0
Summary: A tool that switches gpg home on different working directory
Author-email: GUO YANKE <hi@guoyk.xyz>
Project-URL: Homepage, https://github.com/guoyk93/auto-gpg
Project-URL: Bug Tracker, https://github.com/guoyk93/auto-gpg/issues
Classifier: Programming Language :: Python :: 3
Classifier: License :: OSI Approved :: MIT License
Classifier: Operating System :: OS Independent
Requires-Python: >=3.7
License-File: LICENSE
